hani/__init__.py
hani/app.py
hani/common.py
hani/helpers.py
hani/negotiator.py
hani/run.py
hani/scenario_makers.py
hani/sample_scenarios/Trade/display.py
hani/scenarios/__init__.py
hani/scenarios/base.py
hani/scenarios/trade.py
hani/tools/__init__.py
hani/tools/histograms.py
hani/tools/history.py
hani/tools/outcome_plot.py
hani/tools/preferences.py
hani/tools/random.py
hani/tools/results.py
hani/tools/scenario_info.py
hani/tools/tool.py
hani/tools/urange.py
hani/tools/utility_plot2d.py
hani/tools/helpers/__init__.py
hani-0.1.0.dist-info/METADATA
hani-0.1.0.dist-info/WHEEL
hani-0.1.0.dist-info/entry_points.txt
hani-0.1.0.dist-info/top_level.txt
hani-0.1.0.dist-info/RECORD
